meltPT/__init__.py
meltPT/backtrack_compositions.py
meltPT/fit_melting_paths.py
meltPT/parse.py
meltPT/suite.py
meltPT/thermobarometry.py
meltPT-1.2.1.data/scripts/meltPT
meltPT-1.2.1.dist-info/LICENSE
meltPT-1.2.1.dist-info/METADATA
meltPT-1.2.1.dist-info/WHEEL
meltPT-1.2.1.dist-info/top_level.txt
meltPT-1.2.1.dist-info/RECORD
