Metadata-Version: 2.1
Name: meltPT
Version: 1.2.1
Summary: Calculate pressures and temperatures of melting for basaltic rocks and fit with melting models.
Home-page: https://github.com/fmcnab/meltPT
Author: F. McNab, P. W. Ball
Author-email: mcnab@gfz-potsdam.de
Requires-Python: >=3.7
License-File: LICENSE
Requires-Dist: pandas ~=1.3
Requires-Dist: numpy ~=1.21
Requires-Dist: matplotlib ~=3.5
Requires-Dist: scipy ~=1.7
Requires-Dist: shapely ~=1.8
Requires-Dist: pyMelt ~=1.96
Requires-Dist: pyyaml ~=6.0
Requires-Dist: sympy ~=1.10
Provides-Extra: docs
Requires-Dist: sphinx ~=5.1 ; extra == 'docs'
Requires-Dist: nbsphinx ~=0.8 ; extra == 'docs'
Requires-Dist: nbsphinx-link ~=1.3 ; extra == 'docs'
Requires-Dist: sphinx-rtd-theme ~=1.0 ; extra == 'docs'
Requires-Dist: ipykernel ~=6.15 ; extra == 'docs'
